LICENSE
MANIFEST.in
README.md
requirements.txt
setup.py
jupyter_saagie_plugin.egg-info/PKG-INFO
jupyter_saagie_plugin.egg-info/SOURCES.txt
jupyter_saagie_plugin.egg-info/dependency_links.txt
jupyter_saagie_plugin.egg-info/requires.txt
jupyter_saagie_plugin.egg-info/top_level.txt
saagie/__init__.py
saagie/saagie-button.png
saagie/saagie.js
saagie/saagie.png
saagie/saagie.yml
saagie/server_extension.py
saagie/jinja2/capsule_type_chooser.html
saagie/jinja2/creating_job.html
saagie/jinja2/internal_error.html
saagie/jinja2/job_form.html
saagie/jinja2/login_form.html
saagie/jinja2/logout.html
saagie/jinja2/modal.html
saagie/jinja2/modal_content.html
saagie/jinja2/python_job_form.html
saagie/jinja2/select_python_job.html
saagie/jinja2/started_job.html
saagie/jinja2/starting_job.html
saagie/jinja2/unsupported_kernel.html
saagie/jinja2/update_python_job.html
saagie/jinja2/include/job_details.html
saagie/jinja2/include/python_job_details.html