Metadata-Version: 1.1
Name: jupyter-saagie-plugin
Version: 1.0.6
Summary: Easily create a Saagie Python job from a Jupyter notebook
Home-page: https://github.com/saagie/jupyter-saagie-plugin
Author: Saagie
Author-email: support@saagie.com
License: Apache
Platform: UNKNOWN
Classifier: Development Status :: 5 - Production/Stable
Classifier: Framework :: Django
Classifier: Intended Audience :: Developers
Classifier: License :: OSI Approved :: Apache Software License
Classifier: Operating System :: OS Independent
Classifier: Programming Language :: Python :: 2
Classifier: Programming Language :: Python :: 2.7
Classifier: Programming Language :: Python :: 3
Classifier: Programming Language :: Python :: 3.4
Classifier: Programming Language :: Python :: 3.5
Classifier: Programming Language :: Python :: 3.6
